examples/__init__.py
examples/settings_example1.yaml
examples/settings_example2.yaml
examples/testdata/sample/Drillsample_density_magsus.csv
examples/testdata/sample/gravity_surveysample.tif
examples/testdata/sample/magnetic_TMI-RTP_surveysample.tif
geobo/__init__.py
geobo/config_loader.py
geobo/cubeshow.py
geobo/inversion.py
geobo/kernels.py
geobo/main.py
geobo/run_geobo.py
geobo/run_main.py
geobo/sensormodel.py
geobo/set.py
geobo/setname.py
geobo/settings.yaml
geobo/simcube.py
geobo/utils.py
geobo/tests/__init__.py
geobo/tests/settings_example1.yaml
geobo/tests/settings_example2.yaml
geobo/tests/settings_test.yaml
geobo/tests/testdata/sample/Drillsample_density_magsus.csv
geobo/tests/testdata/sample/gravity_surveysample.tif
geobo/tests/testdata/sample/magnetic_TMI-RTP_surveysample.tif
geobo/tests/testdata/synthetic/figure_simdata_cylinders.png
geobo/tests/testdata/synthetic/figure_simdata_layers_3.png
geobo/tests/testdata/synthetic/gravfield.png
geobo/tests/testdata/synthetic/gravfield_downsampled.png
geobo/tests/testdata/synthetic/gravity_simdata_cylinders.tif
geobo/tests/testdata/synthetic/gravity_simdata_layers_3.tif
geobo/tests/testdata/synthetic/magfield.png
geobo/tests/testdata/synthetic/magfield_downsampled.png
geobo/tests/testdata/synthetic/magnetic_simdata_cylinders.tif
geobo/tests/testdata/synthetic/magnetic_simdata_layers_3.tif
geobo/tests/testdata/synthetic/simcube_cylinders.csv
geobo/tests/testdata/synthetic/simcube_cylinders.vtk
geobo/tests/testdata/synthetic/simcube_layers_3.csv
geobo/tests/testdata/synthetic/simcube_layers_3.vtk
geobo/tests/testdata/synthetic/simdrill_cylinders.csv
geobo/tests/testdata/synthetic/simdrill_layers_3.csv
geobo/tests/testdata/synthetic/simsurveydata_cylinders.csv
geobo/tests/testdata/synthetic/simsurveydata_layers_3.csv
geobo-1.0.0.dist-info/LICENSE.md
geobo-1.0.0.dist-info/METADATA
geobo-1.0.0.dist-info/WHEEL
geobo-1.0.0.dist-info/top_level.txt
geobo-1.0.0.dist-info/RECORD
