Metadata-Version: 2.1
Name: geobo
Version: 1.0.0
Summary: Python package for Multi-Objective Bayesian Optimisation and Joint Inversion in Geosciences
Home-page: https://github.com/sebhaan/geobo
Author: Sebastian Haan
Author-email: sebastian.haan@sydney.edu.au
License: UNKNOWN
Platform: UNKNOWN
Classifier: Programming Language :: Python :: 3
Classifier: Programming Language :: Python :: 3.4
Classifier: Programming Language :: Python :: 3.5
Classifier: Programming Language :: Python :: 3.6
Classifier: Programming Language :: Python :: 3.7
Requires-Python: >=3.6
Requires-Dist: numpy (>=1.15.0)
Requires-Dist: scipy (>=1.1.0)
Requires-Dist: matplotlib (>=2.2.2)
Requires-Dist: scikit-image (>=0.14.0)
Requires-Dist: rasterio (>=1.0.20)
Requires-Dist: pandas (>=0.23.4)
Requires-Dist: pyvista (>=0.23.0)
Requires-Dist: PyYAML (>=5.3)
